ireiat/__init__.py
ireiat/config.py
ireiat/run.py
ireiat/util/__init__.py
ireiat/util/http.py
ireiat/util/logging_.py
ireiat-0.0.1.dist-info/LICENSE
ireiat-0.0.1.dist-info/METADATA
ireiat-0.0.1.dist-info/WHEEL
ireiat-0.0.1.dist-info/entry_points.txt
ireiat-0.0.1.dist-info/top_level.txt
ireiat-0.0.1.dist-info/RECORD
