Metadata-Version: 2.1
Name: ireiat
Version: 0.0.1
Summary: Intermodal Routing and Environmental Impact Analysis Tool
Author-email: Nick Padon <nicholas.padon@oliverwyman.com>, Marc Meketon <marc.meketon@oliverwyman.com>
Classifier: Programming Language :: Python :: 3
Classifier: Operating System :: OS Independent
Requires-Python: >=3.10
License-File: LICENSE
Requires-Dist: click
Requires-Dist: tqdm
Requires-Dist: requests
Requires-Dist: pyyaml
Requires-Dist: pyproj
Requires-Dist: igraph
